[{"value":"sdf","type":"text","name":"sdf","date":"12.04.2021, 21:14"},{"value":"sd","type":"text","name":"sdf","date":"12.04.2021, 21:14"},{"value":"f","type":"text","name":"sdf","date":"12.04.2021, 21:14"},{"value":"sdf","type":"text","name":"sdf","date":"12.04.2021, 21:14"},{"value":"sd","type":"text","name":"sdf","date":"12.04.2021, 21:14"},{"value":"f","type":"text","name":"sdf","date":"12.04.2021, 21:14"},{"value":"fsd","type":"text","name":"sdf","date":"12.04.2021, 21:14"},{"value":"fsd","type":"text","name":"sdf","date":"12.04.2021, 21:14"},{"value":"sdf","type":"text","name":"asdfsdf","date":"12.04.2021, 21:14"},{"value":"sdf","type":"text","name":"asdfsdf","date":"12.04.2021, 21:14"},{"value":"sd","type":"text","name":"asdfsdf","date":"12.04.2021, 21:14"},{"value":"f","type":"text","name":"asdfsdf","date":"12.04.2021, 21:14"},{"value":"sd","type":"text","name":"asdfsdf","date":"12.04.2021, 21:14"},{"value":"f","type":"text","name":"asdfsdf","date":"12.04.2021, 21:14"},{"value":"qweqwe","type":"text","name":"asdasd","date":"12.04.2021, 21:25"},{"value":"qwe","type":"text","name":"asdasd","date":"12.04.2021, 21:25"},{"value":"qwe","type":"text","name":"asdasd","date":"12.04.2021, 21:25"},{"value":"gdfg","type":"text","name":"asdasd","date":"12.04.2021, 21:26"},{"value":"dfgfdg","type":"text","name":"asdasd","date":"12.04.2021, 21:26"}]